{
	"all": {
		"changeLogs": {
			"BDFDB": "3.0.7",
			"BetterFriendList": "1.5.2",
			"BetterNsfwTag": "1.3.2",
			"BetterSearchPage": "1.2.3",
			"CharCounter": "1.6.2",
			"ClickableMentions": "1.0.6",
			"CopyRawMessage": "1.1.4",
			"CreationDate": "9.9.9",
			"EditChannels": "4.5.2",
			"EditRoles": "1.1.4",
			"EditServers": "2.4.1",
			"EditUsers": "4.7.3",
			"JoinedAtDate": "9.9.9",
			"LastMessageDate": "1.3.5",
			"MessageUtilities": "1.9.6",
			"PluginRepo": "2.4.5",
			"ShowHiddenChannels": "9.9.9",
			"ThemeRepo": "2.4.8",
			"TimedLightDarkMode": "1.1.5"
		},
		"choices": {
			"toastPosition": "right"
		},
		"general": {
			"shareData": true,
			"showToasts": true,
			"showSupportBadges": true,
			"useChromium": false
		},
		"hashes": {
			"0BDFDB.data.json": "18ad9a2fe1ffac5d5e63389d5f7d883e540b3911",
			"0BDFDB.raw.css": "a1c4a8b6f28c4765c6af2853ddf13a35922a2b9e"
		}
	}
}